slackertpy/__init__.py
slackertpy/alerter.py
slackertpy/blocks.py
slackertpy/builder.py
slackertpy/level.py
slackertpy/templates.py
tests/__init__.py
tests/test_alerter.py
tests/test_blocks.py
tests/test_templates.py
slackertpy-0.1.2.dist-info/LICENSE
slackertpy-0.1.2.dist-info/METADATA
slackertpy-0.1.2.dist-info/WHEEL
slackertpy-0.1.2.dist-info/top_level.txt
slackertpy-0.1.2.dist-info/RECORD
