Metadata-Version: 2.1
Name: slackertpy
Version: 0.1.2
Summary: Crete and send Slack messages and alerts through a webhook
Home-page: https://github.com/braze-inc/braze-growth-shares-slackertpy
Author: Maciej Olko
License: UNKNOWN
Platform: UNKNOWN
Requires-Dist: requests
